{".class": "MypyFile", "_fullname": "accounts.forms", "is_partial_stub_package": false, "is_stub": false, "names": {".class": "SymbolTable", "GuestForm": {".class": "SymbolTableNode", "kind": "Gdef", "node": {".class": "TypeInfo", "_promote": null, "abstract_attributes": [], "bases": ["builtins.object"], "declared_metaclass": null, "defn": {".class": "ClassDef", "fullname": "accounts.forms.GuestForm", "name": "GuestForm", "type_vars": []}, "flags": ["fallback_to_any"], "fullname": "accounts.forms.GuestForm", "metaclass_type": null, "metadata": {}, "module_name": "accounts.forms", "mro": ["accounts.forms.GuestForm", "builtins.object"], "names": {".class": "SymbolTable", "email": {".class": "SymbolTableNode", "kind": "Mdef", "node": {".class": "Var", "flags": ["is_initialized_in_class"], "fullname": "accounts.forms.GuestForm.email", "name": "email", "type": {".class": "AnyType", "missing_import_name": "accounts.forms.forms", "source_any": {".class": "AnyType", "missing_import_name": "accounts.forms.forms", "source_any": null, "type_of_any": 3}, "type_of_any": 7}}}}, "tuple_type": null, "type_vars": [], "typeddict_type": null}}, "LoginForm": {".class": "SymbolTableNode", "kind": "Gdef", "node": {".class": "TypeInfo", "_promote": null, "abstract_attributes": [], "bases": ["builtins.object"], "declared_metaclass": null, "defn": {".class": "ClassDef", "fullname": "accounts.forms.LoginForm", "name": "LoginForm", "type_vars": []}, "flags": ["fallback_to_any"], "fullname": "accounts.forms.LoginForm", "metaclass_type": null, "metadata": {}, "module_name": "accounts.forms", "mro": ["accounts.forms.LoginForm", "builtins.object"], "names": {".class": "SymbolTable", "email": {".class": "SymbolTableNode", "kind": "Mdef", "node": {".class": "Var", "flags": ["is_initialized_in_class"], "fullname": "accounts.forms.LoginForm.email", "name": "email", "type": {".class": "AnyType", "missing_import_name": "accounts.forms.forms", "source_any": {".class": "AnyType", "missing_import_name": "accounts.forms.forms", "source_any": null, "type_of_any": 3}, "type_of_any": 7}}}, "password": {".class": "SymbolTableNode", "kind": "Mdef", "node": {".class": "Var", "flags": ["is_initialized_in_class"], "fullname": "accounts.forms.LoginForm.password", "name": "password", "type": {".class": "AnyType", "missing_import_name": "accounts.forms.forms", "source_any": {".class": "AnyType", "missing_import_name": "accounts.forms.forms", "source_any": null, "type_of_any": 3}, "type_of_any": 7}}}}, "tuple_type": null, "type_vars": [], "typeddict_type": null}}, "ReadOnlyPasswordHashField": {".class": "SymbolTableNode", "kind": "Gdef", "node": {".class": "Var", "flags": ["is_suppressed_import", "is_ready"], "fullname": "accounts.forms.ReadOnlyPasswordHashField", "name": "ReadOnlyPasswordHashField", "type": {".class": "AnyType", "missing_import_name": "accounts.forms.ReadOnlyPasswordHashField", "source_any": null, "type_of_any": 3}}}, "RegisterForm": {".class": "SymbolTableNode", "kind": "Gdef", "node": {".class": "TypeInfo", "_promote": null, "abstract_attributes": [], "bases": ["builtins.object"], "declared_metaclass": null, "defn": {".class": "ClassDef", "fullname": "accounts.forms.RegisterForm", "name": "RegisterForm", "type_vars": []}, "flags": ["fallback_to_any"], "fullname": "accounts.forms.RegisterForm", "metaclass_type": null, "metadata": {}, "module_name": "accounts.forms", "mro": ["accounts.forms.RegisterForm", "builtins.object"], "names": {".class": "SymbolTable", "Meta": {".class": "SymbolTableNode", "kind": "Mdef", "node": {".class": "TypeInfo", "_promote": null, "abstract_attributes": [], "bases": ["builtins.object"], "declared_metaclass": null, "defn": {".class": "ClassDef", "fullname": "accounts.forms.RegisterForm.Meta", "name": "Meta", "type_vars": []}, "flags": [], "fullname": "accounts.forms.RegisterForm.Meta", "metaclass_type": null, "metadata": {}, "module_name": "accounts.forms", "mro": ["accounts.forms.RegisterForm.Meta", "builtins.object"], "names": {".class": "SymbolTable", "fields": {".class": "SymbolTableNode", "kind": "Mdef", "node": {".class": "Var", "flags": ["is_initialized_in_class"], "fullname": "accounts.forms.RegisterForm.Meta.fields", "name": "fields", "type": {".class": "TupleType", "implicit": false, "items": ["builtins.str", "builtins.str"], "partial_fallback": {".class": "Instance", "args": [{".class": "AnyType", "missing_import_name": null, "source_any": null, "type_of_any": 6}], "type_ref": "builtins.tuple"}}}}, "model": {".class": "SymbolTableNode", "kind": "Mdef", "node": {".class": "Var", "flags": ["is_initialized_in_class"], "fullname": "accounts.forms.RegisterForm.Meta.model", "name": "model", "type": {".class": "CallableType", "arg_kinds": [2, 4], "arg_names": ["_args", "_kwds"], "arg_types": [{".class": "AnyType", "missing_import_name": null, "source_any": null, "type_of_any": 6}, {".class": "AnyType", "missing_import_name": null, "source_any": null, "type_of_any": 6}], "bound_args": [], "def_extras": {}, "fallback": "builtins.type", "implicit": false, "is_ellipsis_args": false, "name": null, "ret_type": "accounts.models.User", "variables": []}}}}, "tuple_type": null, "type_vars": [], "typeddict_type": null}}, "clean": {".class": "SymbolTableNode", "kind": "Mdef", "node": {".class": "FuncDef", "arg_kinds": [0], "arg_names": ["self"], "flags": [], "fullname": "accounts.forms.RegisterForm.clean", "name": "clean", "type": null}}, "clean_password2": {".class": "SymbolTableNode", "kind": "Mdef", "node": {".class": "FuncDef", "arg_kinds": [0], "arg_names": ["self"], "flags": [], "fullname": "accounts.forms.RegisterForm.clean_password2", "name": "clean_password2", "type": null}}, "password1": {".class": "SymbolTableNode", "kind": "Mdef", "node": {".class": "Var", "flags": ["is_initialized_in_class"], "fullname": "accounts.forms.RegisterForm.password1", "name": "password1", "type": {".class": "AnyType", "missing_import_name": "accounts.forms.forms", "source_any": {".class": "AnyType", "missing_import_name": "accounts.forms.forms", "source_any": null, "type_of_any": 3}, "type_of_any": 7}}}, "password2": {".class": "SymbolTableNode", "kind": "Mdef", "node": {".class": "Var", "flags": ["is_initialized_in_class"], "fullname": "accounts.forms.RegisterForm.password2", "name": "password2", "type": {".class": "AnyType", "missing_import_name": "accounts.forms.forms", "source_any": {".class": "AnyType", "missing_import_name": "accounts.forms.forms", "source_any": null, "type_of_any": 3}, "type_of_any": 7}}}, "save": {".class": "SymbolTableNode", "kind": "Mdef", "node": {".class": "FuncDef", "arg_kinds": [0, 1], "arg_names": ["self", "commit"], "flags": [], "fullname": "accounts.forms.RegisterForm.save", "name": "save", "type": null}}}, "tuple_type": null, "type_vars": [], "typeddict_type": null}}, "User": {".class": "SymbolTableNode", "cross_ref": "accounts.models.User", "kind": "Gdef"}, "UserAdminChangeForm": {".class": "SymbolTableNode", "kind": "Gdef", "node": {".class": "TypeInfo", "_promote": null, "abstract_attributes": [], "bases": ["builtins.object"], "declared_metaclass": null, "defn": {".class": "ClassDef", "fullname": "accounts.forms.UserAdminChangeForm", "name": "UserAdminChangeForm", "type_vars": []}, "flags": ["fallback_to_any"], "fullname": "accounts.forms.UserAdminChangeForm", "metaclass_type": null, "metadata": {}, "module_name": "accounts.forms", "mro": ["accounts.forms.UserAdminChangeForm", "builtins.object"], "names": {".class": "SymbolTable", "Meta": {".class": "SymbolTableNode", "kind": "Mdef", "node": {".class": "TypeInfo", "_promote": null, "abstract_attributes": [], "bases": ["builtins.object"], "declared_metaclass": null, "defn": {".class": "ClassDef", "fullname": "accounts.forms.UserAdminChangeForm.Meta", "name": "Meta", "type_vars": []}, "flags": [], "fullname": "accounts.forms.UserAdminChangeForm.Meta", "metaclass_type": null, "metadata": {}, "module_name": "accounts.forms", "mro": ["accounts.forms.UserAdminChangeForm.Meta", "builtins.object"], "names": {".class": "SymbolTable", "fields": {".class": "SymbolTableNode", "kind": "Mdef", "node": {".class": "Var", "flags": ["is_initialized_in_class"], "fullname": "accounts.forms.UserAdminChangeForm.Meta.fields", "name": "fields", "type": {".class": "TupleType", "implicit": false, "items": ["builtins.str", "builtins.str", "builtins.str", "builtins.str", "builtins.str"], "partial_fallback": {".class": "Instance", "args": [{".class": "AnyType", "missing_import_name": null, "source_any": null, "type_of_any": 6}], "type_ref": "builtins.tuple"}}}}, "model": {".class": "SymbolTableNode", "kind": "Mdef", "node": {".class": "Var", "flags": ["is_initialized_in_class"], "fullname": "accounts.forms.UserAdminChangeForm.Meta.model", "name": "model", "type": {".class": "CallableType", "arg_kinds": [2, 4], "arg_names": ["_args", "_kwds"], "arg_types": [{".class": "AnyType", "missing_import_name": null, "source_any": null, "type_of_any": 6}, {".class": "AnyType", "missing_import_name": null, "source_any": null, "type_of_any": 6}], "bound_args": [], "def_extras": {}, "fallback": "builtins.type", "implicit": false, "is_ellipsis_args": false, "name": null, "ret_type": "accounts.models.User", "variables": []}}}}, "tuple_type": null, "type_vars": [], "typeddict_type": null}}, "clean_password": {".class": "SymbolTableNode", "kind": "Mdef", "node": {".class": "FuncDef", "arg_kinds": [0], "arg_names": ["self"], "flags": [], "fullname": "accounts.forms.UserAdminChangeForm.clean_password", "name": "clean_password", "type": null}}, "password": {".class": "SymbolTableNode", "kind": "Mdef", "node": {".class": "Var", "flags": ["is_initialized_in_class"], "fullname": "accounts.forms.UserAdminChangeForm.password", "name": "password", "type": {".class": "AnyType", "missing_import_name": "accounts.forms.ReadOnlyPasswordHashField", "source_any": {".class": "AnyType", "missing_import_name": "accounts.forms.ReadOnlyPasswordHashField", "source_any": null, "type_of_any": 3}, "type_of_any": 7}}}}, "tuple_type": null, "type_vars": [], "typeddict_type": null}}, "UserAdminCreationForm": {".class": "SymbolTableNode", "kind": "Gdef", "node": {".class": "TypeInfo", "_promote": null, "abstract_attributes": [], "bases": ["builtins.object"], "declared_metaclass": null, "defn": {".class": "ClassDef", "fullname": "accounts.forms.UserAdminCreationForm", "name": "UserAdminCreationForm", "type_vars": []}, "flags": ["fallback_to_any"], "fullname": "accounts.forms.UserAdminCreationForm", "metaclass_type": null, "metadata": {}, "module_name": "accounts.forms", "mro": ["accounts.forms.UserAdminCreationForm", "builtins.object"], "names": {".class": "SymbolTable", "Meta": {".class": "SymbolTableNode", "kind": "Mdef", "node": {".class": "TypeInfo", "_promote": null, "abstract_attributes": [], "bases": ["builtins.object"], "declared_metaclass": null, "defn": {".class": "ClassDef", "fullname": "accounts.forms.UserAdminCreationForm.Meta", "name": "Meta", "type_vars": []}, "flags": [], "fullname": "accounts.forms.UserAdminCreationForm.Meta", "metaclass_type": null, "metadata": {}, "module_name": "accounts.forms", "mro": ["accounts.forms.UserAdminCreationForm.Meta", "builtins.object"], "names": {".class": "SymbolTable", "fields": {".class": "SymbolTableNode", "kind": "Mdef", "node": {".class": "Var", "flags": ["is_initialized_in_class"], "fullname": "accounts.forms.UserAdminCreationForm.Meta.fields", "name": "fields", "type": {".class": "TupleType", "implicit": false, "items": ["builtins.str", "builtins.str"], "partial_fallback": {".class": "Instance", "args": [{".class": "AnyType", "missing_import_name": null, "source_any": null, "type_of_any": 6}], "type_ref": "builtins.tuple"}}}}, "model": {".class": "SymbolTableNode", "kind": "Mdef", "node": {".class": "Var", "flags": ["is_initialized_in_class"], "fullname": "accounts.forms.UserAdminCreationForm.Meta.model", "name": "model", "type": {".class": "CallableType", "arg_kinds": [2, 4], "arg_names": ["_args", "_kwds"], "arg_types": [{".class": "AnyType", "missing_import_name": null, "source_any": null, "type_of_any": 6}, {".class": "AnyType", "missing_import_name": null, "source_any": null, "type_of_any": 6}], "bound_args": [], "def_extras": {}, "fallback": "builtins.type", "implicit": false, "is_ellipsis_args": false, "name": null, "ret_type": "accounts.models.User", "variables": []}}}}, "tuple_type": null, "type_vars": [], "typeddict_type": null}}, "clean_password2": {".class": "SymbolTableNode", "kind": "Mdef", "node": {".class": "FuncDef", "arg_kinds": [0], "arg_names": ["self"], "flags": [], "fullname": "accounts.forms.UserAdminCreationForm.clean_password2", "name": "clean_password2", "type": null}}, "password1": {".class": "SymbolTableNode", "kind": "Mdef", "node": {".class": "Var", "flags": ["is_initialized_in_class"], "fullname": "accounts.forms.UserAdminCreationForm.password1", "name": "password1", "type": {".class": "AnyType", "missing_import_name": "accounts.forms.forms", "source_any": {".class": "AnyType", "missing_import_name": "accounts.forms.forms", "source_any": null, "type_of_any": 3}, "type_of_any": 7}}}, "password2": {".class": "SymbolTableNode", "kind": "Mdef", "node": {".class": "Var", "flags": ["is_initialized_in_class"], "fullname": "accounts.forms.UserAdminCreationForm.password2", "name": "password2", "type": {".class": "AnyType", "missing_import_name": "accounts.forms.forms", "source_any": {".class": "AnyType", "missing_import_name": "accounts.forms.forms", "source_any": null, "type_of_any": 3}, "type_of_any": 7}}}, "save": {".class": "SymbolTableNode", "kind": "Mdef", "node": {".class": "FuncDef", "arg_kinds": [0, 1], "arg_names": ["self", "commit"], "flags": [], "fullname": "accounts.forms.UserAdminCreationForm.save", "name": "save", "type": null}}}, "tuple_type": null, "type_vars": [], "typeddict_type": null}}, "__doc__": {".class": "SymbolTableNode", "kind": "Gdef", "node": {".class": "Var", "flags": ["is_ready"], "fullname": "accounts.forms.__doc__", "name": "__doc__", "type": "builtins.str"}}, "__file__": {".class": "SymbolTableNode", "kind": "Gdef", "node": {".class": "Var", "flags": ["is_ready"], "fullname": "accounts.forms.__file__", "name": "__file__", "type": "builtins.str"}}, "__name__": {".class": "SymbolTableNode", "kind": "Gdef", "node": {".class": "Var", "flags": ["is_ready"], "fullname": "accounts.forms.__name__", "name": "__name__", "type": "builtins.str"}}, "__package__": {".class": "SymbolTableNode", "kind": "Gdef", "node": {".class": "Var", "flags": ["is_ready"], "fullname": "accounts.forms.__package__", "name": "__package__", "type": "builtins.str"}}, "forms": {".class": "SymbolTableNode", "kind": "Gdef", "node": {".class": "Var", "flags": ["is_suppressed_import", "is_ready"], "fullname": "accounts.forms.forms", "name": "forms", "type": {".class": "AnyType", "missing_import_name": "accounts.forms.forms", "source_any": null, "type_of_any": 3}}}, "get_user_model": {".class": "SymbolTableNode", "kind": "Gdef", "node": {".class": "Var", "flags": ["is_suppressed_import", "is_ready"], "fullname": "accounts.forms.get_user_model", "name": "get_user_model", "type": {".class": "AnyType", "missing_import_name": "accounts.forms.get_user_model", "source_any": null, "type_of_any": 3}}}}, "path": "/home/nurudeen/Documents/ecommerce/accounts/forms.py"}